jl_metric/__init__.py
jl_metric/metric.py
jl_metric-0.1.1.dist-info/METADATA
jl_metric-0.1.1.dist-info/WHEEL
jl_metric-0.1.1.dist-info/top_level.txt
jl_metric-0.1.1.dist-info/RECORD
