Metadata-Version: 2.4
Name: jl-metric
Version: 0.1.1
Summary: A Johnson-Lindenstrauss-based metric for dynamic graph generative model evaluation
Home-page: https://github.com/ryienh/jl-metric
Author: Ryien Hosseini
Author-email: ryien@uchicago.edu
Project-URL: Bug Tracker, https://github.com/ryienh/jl-metric/issues
Keywords: graph-learning,dynamic-graphs,generative-models
Classifier: Programming Language :: Python :: 3
Classifier: License :: OSI Approved :: MIT License
Classifier: Operating System :: OS Independent
Classifier: Topic :: Scientific/Engineering :: Artificial Intelligence
Classifier: Topic :: Scientific/Engineering :: Mathematics
Requires-Python: >=3.7
Requires-Dist: torch>=1.9.0
Requires-Dist: torch-geometric>=2.0.0
Requires-Dist: numpy>=1.19.0
Dynamic: author
Dynamic: author-email
Dynamic: classifier
Dynamic: description
Dynamic: description-content-type
Dynamic: home-page
Dynamic: keywords
Dynamic: project-url
Dynamic: requires-dist
Dynamic: requires-python
Dynamic: summary
